README.md
nautobot_chatops_arista_cloudvision/__init__.py
nautobot_chatops_arista_cloudvision/cvpgrpcutils.py
nautobot_chatops_arista_cloudvision/static/nautobot_cloudvision/cloudvision_logo.png
nautobot_chatops_arista_cloudvision/tests/__init__.py
nautobot_chatops_arista_cloudvision/tests/test_api.py
nautobot_chatops_arista_cloudvision/tests/test_basic.py
nautobot_chatops_arista_cloudvision/utils.py
nautobot_chatops_arista_cloudvision/worker.py
nautobot_chatops_arista_cloudvision-1.3.0.dist-info/METADATA
nautobot_chatops_arista_cloudvision-1.3.0.dist-info/WHEEL
nautobot_chatops_arista_cloudvision-1.3.0.dist-info/entry_points.txt
nautobot_chatops_arista_cloudvision-1.3.0.dist-info/RECORD
