Metadata-Version: 2.1
Name: nautobot-chatops-arista-cloudvision
Version: 1.3.0
Summary: Nautobot Chatops Arista Cloudvision Integration
Home-page: https://github.com/nautobot/nautobot-plugin-chatops-arista-cloudvision
License: Apache-2.0
Keywords: nautobot,nautobot-plugin
Author: Network to Code, LLC
Author-email: info@networktocode.com
Requires-Python: >=3.8,<4.0
Classifier: License :: OSI Approved :: Apache Software License
Classifier: Programming Language :: Python :: 3
Classifier: Programming Language :: Python :: 3.8
Classifier: Programming Language :: Python :: 3.9
Classifier: Programming Language :: Python :: 3.10
Classifier: Programming Language :: Python :: 3.11
Provides-Extra: nautobot
Requires-Dist: cloudvision (>=1.1,<2.0)
Requires-Dist: cvprac (>=1.0.6,<2.0.0)
Requires-Dist: nautobot (>=1.5.9,<2.0.0) ; extra == "nautobot"
Requires-Dist: nautobot-chatops (>=1.5.0,<2.0.0)
Requires-Dist: protobuf (>=3.17,<4.0)
Project-URL: Repository, https://github.com/nautobot/nautobot-plugin-chatops-arista-cloudvision
